{
	"animations": [
		{
			"loop": false,
			"offsets": [
				0,
				0
			],
			"anim": "danceLeft",
			"fps": 24,
			"name": "DanceLeft",
			"indices": []
		},
		{
			"loop": false,
			"offsets": [
				0,
				0
			],
			"anim": "danceRight",
			"fps": 24,
			"name": "DanceRight",
			"indices": []
		},
		{
			"loop": false,
			"offsets": [
				-60,
				-30
			],
			"anim": "singLEFT",
			"fps": 24,
			"name": "Left",
			"indices": []
		},
		{
			"loop": false,
			"offsets": [
				-332,
				-223
			],
			"anim": "singDOWN",
			"fps": 24,
			"name": "Down",
			"indices": []
		},
		{
			"loop": false,
			"offsets": [
				-230,
				30
			],
			"anim": "singUP",
			"fps": 24,
			"name": "Up",
			"indices": []
		},
		{
			"loop": false,
			"offsets": [
				-261,
				-40
			],
			"anim": "singRIGHT",
			"fps": 24,
			"name": "Right",
			"indices": []
		}
	],
	"no_antialiasing": false,
	"image": "characters/Osha Figure Shiny",
	"position": [
		-280,
		190
	],
	"healthicon": "OshawottFigure",
	"flip_x": false,
	"healthbar_colors": [
		63,
		130,
		255
	],
	"camera_position": [
		0,
		0
	],
	"sing_duration": 6.1,
	"scale": 1
}